{"ABILITY-16650-DOTD-98286": {"_id": "ABILITY-16650-DOTD-98286", "_target": "self", "ability_type": "Restore", "description": "Heals the users mod", "level": 0, "mod": {"adds": {}, "mults": {"energy": 0.45}}, "name": "Heal"}, "ABILITY-16650-DXUF-98274": {"_id": "ABILITY-16650-DXUF-98274", "_target": "self", "ability_type": "Buff", "description": "Strengthens player", "level": 0, "mod": {"adds": {}, "mults": {"defense": 0.98}}, "name": "Empower"}, "ABILITY-16650-OKNG-98180": {"_id": "ABILITY-16650-OKNG-98180", "_target": "enemy", "ability_type": "Magic", "description": "Throws a fireball at target", "level": 0, "mod": {"adds": {"defense": -446}, "mults": {}}, "name": "Fireball"}, "ABILITY-16659-LDHB-46504": {"_id": "ABILITY-16659-LDHB-46504", "_target": "enemy", "ability_type": "Magic", "description": "Sends a cooling chill to the enemy and freezes them on the spot", "level": 0, "mod": {"adds": {"health": -322}, "mults": {}}, "name": "Freeze"}, "ABILITY-16659-NYWC-46543": {"_id": "ABILITY-16659-NYWC-46543", "_target": "enemy", "ability_type": "Physical", "description": "Strikes an enemy with the users weapon", "level": 0, "mod": {"adds": {"health": -225}, "mults": {}}, "name": "Strike"}, "ABILITY-16660-TXKX-31305": {"_id": "ABILITY-16660-TXKX-31305", "_target": "enemy", "ability_type": "Debuff", "description": "Weakens an enemy", "level": 0, "mod": {"adds": {}, "mults": {"defense": -0.83}}, "name": "Weaken"}, "ABILITY-16694-TRKE-96324": {"_id": "ABILITY-16694-TRKE-96324", "_target": "enemy", "ability_type": "Magic", "description": "Sends a bolt of lightning towards the enemy", "level": 0, "mod": {"adds": {"health": -240}, "mults": {}}, "name": "Lightning"}, "ABILITY-16694-ZGOD-96259": {"_id": "ABILITY-16694-ZGOD-96259", "_target": "self", "ability_type": "Buff", "description": "Boost the speed of the caster", "level": 0, "mod": {"adds": {}, "mults": {"health": 0.5}}, "name": "Speed Boost"}}